LICENSE
MANIFEST.in
README.md
example_testplan_01.py
setup.py
jmeter_api/__init__.py
jmeter_api/assertions/__init__.py
jmeter_api/assertions/duration/__init__.py
jmeter_api/assertions/duration/elements.py
jmeter_api/assertions/duration/template.xml
jmeter_api/assertions/duration/test_duration_assertion.py
jmeter_api/assertions/json/__init__.py
jmeter_api/assertions/json/elements.py
jmeter_api/assertions/json/template.xml
jmeter_api/assertions/json/test_json_assertion.py
jmeter_api/assertions/jsr223/__init__.py
jmeter_api/assertions/jsr223/elements.py
jmeter_api/assertions/jsr223/template.xml
jmeter_api/assertions/jsr223/test_jsr223_assertion.py
jmeter_api/assertions/response/__init__.py
jmeter_api/assertions/response/elements.py
jmeter_api/assertions/response/template.xml
jmeter_api/assertions/response/test_response_assertion.py
jmeter_api/assertions/size/__init__.py
jmeter_api/assertions/size/elements.py
jmeter_api/assertions/size/template.xml
jmeter_api/assertions/size/test_size_assertion.py
jmeter_api/basics/__init__.py
jmeter_api/basics/jsr223.py
jmeter_api/basics/test_jsr223.py
jmeter_api/basics/test_utils.py
jmeter_api/basics/utils.py
jmeter_api/basics/assertion/__init__.py
jmeter_api/basics/assertion/elements.py
jmeter_api/basics/config/__init__.py
jmeter_api/basics/config/elements.py
jmeter_api/basics/controller/__init__.py
jmeter_api/basics/controller/elements.py
jmeter_api/basics/controller/test_basic_conroller.py
jmeter_api/basics/element/__init__.py
jmeter_api/basics/element/elements.py
jmeter_api/basics/element/test_basics_elements.py
jmeter_api/basics/listener/__init__.py
jmeter_api/basics/listener/elements.py
jmeter_api/basics/listener/result_collector_template.xml
jmeter_api/basics/listener/test_result_collector.py
jmeter_api/basics/non_test_elements/__init__.py
jmeter_api/basics/non_test_elements/elements.py
jmeter_api/basics/post_processor/__init__.py
jmeter_api/basics/post_processor/elements.py
jmeter_api/basics/pre_processor/__init__.py
pyjmeter.egg-info/PKG-INFO
pyjmeter.egg-info/SOURCES.txt
pyjmeter.egg-info/dependency_links.txt
pyjmeter.egg-info/requires.txt
pyjmeter.egg-info/top_level.txt