Metadata-Version: 2.1
Name: pyjmeter
Version: 0.5.1
Summary: JMeter test plan builder
Home-page: https://github.com/lanitgithub/jmeter_api
Author: Alexey Svetlov
Author-email: alexeysvetlov92@gmail.com
License: UNKNOWN
Project-URL: Source, https://github.com/lanitgithub/jmeter_api
Platform: UNKNOWN
Classifier: Development Status :: 3 - Alpha
Classifier: Topic :: Software Development :: Testing
Classifier: License :: OSI Approved :: Apache Software License
Classifier: Programming Language :: Python :: 3
Classifier: Programming Language :: Python :: 3.6
Classifier: Programming Language :: Python :: 3.7
Requires-Python: >=3.6
